print_color/__init__.py
print_color/print_color.py
print_color-0.4.5.dist-info/LICENSE
print_color-0.4.5.dist-info/WHEEL
print_color-0.4.5.dist-info/METADATA
print_color-0.4.5.dist-info/RECORD
