Metadata-Version: 2.1
Name: print-color
Version: 0.4.5
Summary: A simple package to print in color to the terminal
Home-page: https://github.com/xy3/print-color
License: MIT
Author: xy3
Author-email: a@xsq.pw
Requires-Python: >=3.6,<4.0
Classifier: License :: OSI Approved :: MIT License
Classifier: Programming Language :: Python :: 3
Classifier: Programming Language :: Python :: 3.10
Classifier: Programming Language :: Python :: 3.6
Classifier: Programming Language :: Python :: 3.7
Classifier: Programming Language :: Python :: 3.8
Classifier: Programming Language :: Python :: 3.9
Requires-Dist: pytest (>=6.2.5,<7.0.0)
Project-URL: Repository, https://github.com/xy3/print-color
